scMINGLE/__init__.py
scMINGLE/contrast_tools.py
scMINGLE/data_processing.py
scMINGLE/network.py
scMINGLE-1.1.0.data/data/MINGLE.png
scMINGLE-1.1.0.dist-info/LICENSE.txt
scMINGLE-1.1.0.dist-info/METADATA
scMINGLE-1.1.0.dist-info/WHEEL
scMINGLE-1.1.0.dist-info/top_level.txt
scMINGLE-1.1.0.dist-info/RECORD
